dima/__init__.py
dima/ann.py
dima/ddpm.py
dima/dima.py
dima/dmap.py
dima/gplm.py
dima/utils.py
dima-0.1.6.dist-info/licenses/LICENSE
dima-0.1.6.dist-info/METADATA
dima-0.1.6.dist-info/WHEEL
dima-0.1.6.dist-info/top_level.txt
dima-0.1.6.dist-info/RECORD
