Metadata-Version: 2.4
Name: dima
Version: 0.1.6
Summary: DIMA: Diffusion–Isocoder Manifold-Autoencoder
Author: Julio Candanedo
License: MIT
Requires-Python: >=3.10
License-File: LICENSE
Requires-Dist: numpy>=1.24
Requires-Dist: scipy>=1.10
Requires-Dist: jax>=0.4.20
Requires-Dist: jaxlib>=0.4.20
Requires-Dist: flax>=0.8
Requires-Dist: optax>=0.2
Requires-Dist: huggingface_hub>=0.22
Requires-Dist: faiss-cpu>=1.7.4
Provides-Extra: viz
Requires-Dist: matplotlib>=3.7; extra == "viz"
Provides-Extra: dev
Requires-Dist: pytest>=7; extra == "dev"
Requires-Dist: ruff>=0.4; extra == "dev"
Requires-Dist: mypy>=1.8; extra == "dev"
Requires-Dist: pre-commit>=3.6; extra == "dev"
Requires-Dist: build>=1.2; extra == "dev"
Requires-Dist: twine>=5; extra == "dev"
Dynamic: license-file
